Workbook

Sheet Summary
A1: Step 6 status: tenant-aware authentication and authorization
A2: Change the yellow Status cells on the other sheets; the counts below recalculate.
A4: Status | B4: Guide requirements | C4: Sub-steps and tasks | D4: Tests (count)
A5: Done | B5: =COUNTIF(Requirements!$D$2:$D$8,A5) -> 4 | C5: =COUNTIF('Sub-steps'!$C$2:$C$33,A5) -> 10 | D5: =SUMIF(Tests!$D$2:$D$6,A5,Tests!$C$2:$C$6) -> 5
A6: Ready to build | B6: =COUNTIF(Requirements!$D$2:$D$8,A6) -> 3 | C6: =COUNTIF('Sub-steps'!$C$2:$C$33,A6) -> 14 | D6: =SUMIF(Tests!$D$2:$D$6,A6,Tests!$C$2:$C$6) -> 23
A7: Pending | B7: =COUNTIF(Requirements!$D$2:$D$8,A7) -> 0 | C7: =COUNTIF('Sub-steps'!$C$2:$C$33,A7) -> 8 | D7: =SUMIF(Tests!$D$2:$D$6,A7,Tests!$C$2:$C$6) -> 0
A8: Total | B8: =SUM(B5:B7) -> 7 | C8: =SUM(C5:C7) -> 32 | D8: =SUM(D5:D7) -> 28
A9: Share done | B9: =IF(B8=0,0,B5/B8) -> 0.57142857 | C9: =IF(C8=0,0,C5/C8) -> 0.3125 | D9: =IF(D8=0,0,D5/D8) -> 0.17857143
A11: Status meanings
A12: Roadmap steps 6-16: see 'Versions' sheet for progress per version.
A13: Ready to build: full steps and code have been given; not yet built or confirmed by you.
A14: Pending: not started, or deferred to a later step.
A16: How to use
A17: Yellow cells (Status) are the only cells to edit. Pick Done, Ready to build or Pending from the list.
A18: Requirements: the seven points from the Step 6 guide and how well each is covered.
A19: Sub-steps: the work items in order. 'Beyond guide' items come from the security design; 'Before production' items are release blockers.
A20: Tests: expected test counts per class. The total should reach 28 when Step 6 is complete.

Sheet Build Order
A1: Order | B1: Slice | C1: Priority tier | D1: Name | E1: What you get | F1: Tasks | G1: Done | H1: Task IDs | I1: App works when
A2: 1 | B2: C1 | C2: P0 Critical | D2: Secure foundation | E2: Sign in, tenant isolation, platform admin creates shops, rate limiting and headers. | F2: =COUNTIF('Roadmap 6-16'!$N$2:$N$152,B2) -> 21 | G2: =COUNTIFS('Roadmap 6-16'!$N$2:$N$152,B2,'Roadmap 6-16'!$L$2:$L$152,"Done") -> 18 | H2: 6.1, 6.2, 6.3, 6.4, 6.5, 6.6, 6.7, 6.8, 6.9, 6.10, 6.10b, 6.11a, 6.11b, 6.11c, 6.11d, 6.12a, 6.12b, 6.12c, 6.12e, 6.13c, 6.13d | I2: dotnet test passes; login works; platform admin creates a tenant; /health/live shows security headers.
A3: 2 | B3: C2 | C3: P0 Critical | D3: Core data model | E3: Branch, categories, products, sales, payments, stock ledger and balance, settings, receipt counters. | F3: =COUNTIF('Roadmap 6-16'!$N$2:$N$152,B3) -> 11 | G3: =COUNTIFS('Roadmap 6-16'!$N$2:$N$152,B3,'Roadmap 6-16'!$L$2:$L$152,"Done") -> 0 | H3: 7.1, 7.2, 7.3, 7.4, 7.5, 7.6, 7.11, 7.12, 7.13, 7.15, 7.17 | I3: Migration applied; \dt shows the tables; app starts; all tests still pass.
A4: 3 | B4: C3 | C4: P0 Critical | D4: Products and opening stock | E4: Create and list products with opening stock; other shops cannot see them. | F4: =COUNTIF('Roadmap 6-16'!$N$2:$N$152,B4) -> 4 | G4: =COUNTIFS('Roadmap 6-16'!$N$2:$N$152,B4,'Roadmap 6-16'!$L$2:$L$152,"Done") -> 0 | H4: 8.2, 8.3, 8.5, 8.10 | I4: Create a product with opening stock through the API; isolation tests pass.
A5: 4 | B5: C4 | C5: P0 Critical | D5: Checkout engine | E5: Price maths, receipt numbers, one-transaction sale, cash and M-Pesa, safe retries. | F5: =COUNTIF('Roadmap 6-16'!$N$2:$N$152,B5) -> 11 | G5: =COUNTIFS('Roadmap 6-16'!$N$2:$N$152,B5,'Roadmap 6-16'!$L$2:$L$152,"Done") -> 0 | H5: 9.1, 9.3, 9.4, 9.5, 9.7, 9.8, 6.15, 9.19, 11.1, 11.2, 11.3 | I5: POST /sales records a sale, takes stock out, and the same saleId sent twice makes one sale.
A6: 5 | B6: C5 | C6: P0 Critical | D6: Sale in the browser | E6: Sign-in screen, product screens, POS screen, payment, receipt. | F6: =COUNTIF('Roadmap 6-16'!$N$2:$N$152,B6) -> 10 | G6: =COUNTIFS('Roadmap 6-16'!$N$2:$N$152,B6,'Roadmap 6-16'!$L$2:$L$152,"Done") -> 0 | H6: 10.1, 10.2, 10.3, 10.4, 8.7, 8.8, 10.5, 10.6, 10.7, 10.16 | I6: A cashier signs in and completes a cash sale in the browser and prints a receipt.
A7: 6 | B7: C6 | C7: P0 Critical | D7: Go live with one shop | E7: Production settings, hosted, migrations, backups, pilot. | F7: =COUNTIF('Roadmap 6-16'!$N$2:$N$152,B7) -> 6 | G7: =COUNTIFS('Roadmap 6-16'!$N$2:$N$152,B7,'Roadmap 6-16'!$L$2:$L$152,"Done") -> 0 | H7: 15.5, 14.9, 16.1, 16.2, 16.3, 16.5 | I7: Backup restores; one real shop sells for a week with no data loss.
A8: 7 | B8: H1 | C8: P1 High | D8: Harden and audit | E8: Audit log, platform tests, hardening tests, real client IP, platform admin MFA, concurrency test. | F8: =COUNTIF('Roadmap 6-16'!$N$2:$N$152,B8) -> 9 | G8: =COUNTIFS('Roadmap 6-16'!$N$2:$N$152,B8,'Roadmap 6-16'!$L$2:$L$152,"Done") -> 0 | H8: 6.12d, 6.12f, 6.13a, 6.13b, 6.13e, 6.14, 6.16, 6.18, 11.7 | I8: Security events visible in audit table; 28 tests pass; two sales of the last unit cannot both succeed.
A9: 8 | B9: H2 | C9: P1 High | D9: Daily shop operations | E9: Categories, barcode scan, settings screen, negative stock rule, sales history, void. | F9: =COUNTIF('Roadmap 6-16'!$N$2:$N$152,B9) -> 7 | G9: =COUNTIFS('Roadmap 6-16'!$N$2:$N$152,B9,'Roadmap 6-16'!$L$2:$L$152,"Done") -> 0 | H9: 8.1, 8.6, 9.2, 9.6, 9.10, 9.11, 10.8 | I9: Owner can review the day, void a mistake, and scan a barcode.
A10: 9 | B10: H3 | C10: P1 High | D10: Stock management | E10: Receive stock, adjust, stock levels and history with screens. | F10: =COUNTIF('Roadmap 6-16'!$N$2:$N$152,B10) -> 4 | G10: =COUNTIFS('Roadmap 6-16'!$N$2:$N$152,B10,'Roadmap 6-16'!$L$2:$L$152,"Done") -> 0 | H10: 9.13, 9.14, 9.15, 10.10 | I10: Receiving a delivery raises on-hand; adjustments appear in history.
A11: 10 | B11: H4 | C11: P1 High | D11: Reports, staff and docs | E11: Daily report, user management, config, README, restricted DB user, compliance review. | F11: =COUNTIF('Roadmap 6-16'!$N$2:$N$152,B11) -> 8 | G11: =COUNTIFS('Roadmap 6-16'!$N$2:$N$152,B11,'Roadmap 6-16'!$L$2:$L$152,"Done") -> 0 | H11: 9.16, 10.9, 10.11, 10.15, 15.1, 15.2, 16.4, 16.6 | I11: Owner adds a cashier; daily report matches manual total.
A12: 11 | B12: H5 | C12: P1 High | D12: Offline foundation | E12: PWA, local database, offline checkout, queue states. | F12: =COUNTIF('Roadmap 6-16'!$N$2:$N$152,B12) -> 8 | G12: =COUNTIFS('Roadmap 6-16'!$N$2:$N$152,B12,'Roadmap 6-16'!$L$2:$L$152,"Done") -> 0 | H12: 12.1, 12.2, 12.3, 12.4, 12.5, 12.6, 12.10, 7.8 | I12: Sell with the network off; sales wait in the local queue.
A13: 12 | B13: H6 | C13: P1 High | D13: Safe sync | E13: Sync endpoint, idempotency, retry, conflicts, pull changes. | F13: =COUNTIF('Roadmap 6-16'!$N$2:$N$152,B13) -> 7 | G13: =COUNTIFS('Roadmap 6-16'!$N$2:$N$152,B13,'Roadmap 6-16'!$L$2:$L$152,"Done") -> 0 | H13: 13.1, 13.2, 13.3, 13.4, 13.5, 13.7, 13.10 | I13: Reconnect and sync with zero duplicate sales.
... A21: 20 | B21: L1 | C21: P4 Low | D21: Can do without | E21: Product images, customers table, support sessions, suppliers, dedicated installs, multi-terminal reservation. | F21: =COUNTIF('Roadmap 6-16'!$N$2:$N$152,B21) -> 6 | G21: =COUNTIFS('Roadmap 6-16'!$N$2:$N$152,B21,'Roadmap 6-16'!$L$2:$L$152,"Done") -> 0 | H21: 6.19, 7.10, 8.12, 9.18, 13.11, 14.10 | I21: Only if a customer needs it.
A23: How to use: finish a slice completely (build, tests green, run the app, check the 'App works when' column), commit, then start the next slice.
A24: Never start a slice in a lower tier while a higher tier slice is unfinished, unless a task there is a listed dependency.
A25: Each slice leaves the app runnable. Tests for a feature are added in the slice that builds it.
A26: Some tasks were moved up so no tier is blocked by a lower one: 6.13c, 6.13d, 7.12, 8.5, 15.5 to Critical; 6.13e and 7.8 to High; 7.9 to Medium.
A27: Dependencies were adjusted for the same reason, e.g. 7.17 now covers only the critical tables, and 10.16 needs 10.1-10.7 only.

Sheet Roadmap 6-16
A1: ID | B1: Step | C1: Task | D1: What to build (detail) | E1: Why it matters | F1: Done when (acceptance) | G1: Version | H1: Priority | I1: Layer | J1: Depends on | K1: Effort | L1: Status | M1: My decision / notes | N1: Build slice
A2: 6.1 | B2: 6 Auth & authorization | C2: Domain base types | D2: ITenantOwned interface and TenantEntity base class (Id, TenantId, CreatedAtUtc, UpdatedAtUtc). | E2: One shared rule for what 'belongs to a tenant' lets the DbContext enforce isolation generically. | F2: Product and later entities inherit it; project builds. | G2: v1.0 | H2: P0 Critical | I2: Domain | K2: S | L2: Done | N2: C1
A3: 6.2 | B3: 6 Auth & authorization | C3: Permissions and system roles | D3: Permission string catalogue (products.read, products.write, ...), Role and RolePermission entities; roles Owner, Manager, Cashier, StockController. | E3: Permissions, not role names, are checked in code so roles can change without code edits. | F3: Role-permission rows seeded and readable. | G3: v1.0 | H3: P0 Critical | I3: DB | J3: 6.1 | K3: M | L3: Done | N3: C1
A4: 6.3 | B4: 6 Auth & authorization | C4: Tenant, TenantMembership, Product entities | D4: Tenant(Status, Name), TenantMembership(UserId, TenantId, RoleId, Status), Product with TenantId. | E4: User-to-tenant link with a role is the core of multi-tenancy; a user outside a tenant has no access. | F4: Tables mapped with unique (UserId, TenantId). | G4: v1.0 | H4: P0 Critical | I4: DB | J4: 6.1 | K4: M | L4: Done | N4: C1
A5: 6.4 | B5: 6 Auth & authorization | C5: Tenant context abstraction and AppUser | D5: ITenantContext (TenantId, UserId) and AppUser : IdentityUser<Guid>. | E5: Keeps tenant lookup out of controllers and allows a test implementation. | F5: Context resolved from claims in API; fake in tests. | G5: v1.0 | H5: P0 Critical | I5: Domain | J5: 6.3 | K5: S | L5: Done | N5: C1
A6: 6.5 | B6: 6 Auth & authorization | C6: AppDbContext: Identity, query filter, SaveChanges rules | D6: IdentityUserContext, global query filter on ITenantOwned by current TenantId, SaveChanges stamps TenantId and rejects cross-tenant writes. | E6: Even a forgotten Where clause cannot leak another tenant's rows. | F6: Query without tenant returns nothing; write to other tenant throws. | G6: v1.0 | H6: P0 Critical | I6: DB | J6: 6.4 | K6: L | L6: Done | N6: C1
A7: 6.6 | B7: 6 Auth & authorization | C7: Tenant isolation tests | D7: 5 tests proving read/write isolation at DbContext level against pos_test. | E7: Guide requires tests that prove denial. | F7: 5 tests green. | G7: v1.0 | H7: P0 Critical | I7: Test | J7: 6.5 | K7: M | L7: Done | N7: C1
A8: 6.7 | B8: 6 Auth & authorization | C8: Migration AddIdentityAndTenancy | D8: Create and apply the first identity/tenant migration to pos_dev. | E8: Schema is repeatable from code. | F8: dotnet ef database update succeeds. | G8: v1.0 | H8: P0 Critical | I8: DB | J8: 6.5 | K8: S | L8: Done | N8: C1
A9: 6.8 | B9: 6 Auth & authorization | C9: Seed roles, demo tenant and owner | D9: DevSeeder creates roles and permissions, Demo Shop tenant, owner from Seed:OwnerEmail/Seed:OwnerPassword (user-secrets). | E9: Gives a sign-in without hard-coded credentials, per guide. | F9: Owner can sign in; no password in source control. | G9: v1.0 | H9: P0 Critical | I9: API | J9: 6.7 | K9: M | L9: Done | N9: C1
A10: 6.9 | B10: 6 Auth & authorization | C10: Sign-in, JWT with sub and tid, /me | D10: POST /auth/login validates password, lockout (5 attempts/15 min), issues 15-minute JWT with sub, tid, jti. GET /me returns user, tenant, role, permissions. | E10: Tenant comes from the signed token, never from the browser request. | F10: Login returns token; /me shows correct tenant. | G10: v1.0 | H10: P0 Critical | I10: API | J10: 6.8 | K10: L | L10: Done | N10: C1
A11: 6.10 | B11: 6 Auth & authorization | C11: Permission policies, default-deny, product endpoints | D11: One authorization policy per permission; PermissionHandler re-checks active membership, tenant status and role permission per request; FallbackPolicy denies by default; other tenants' records return 404. | E11: Revoked users lose access immediately, not at token expiry. | F11: Anonymous call to any non-public endpoint returns 401. | G11: v1.0 | H11: P0 Critical | I11: API | J11: 6.9 | K11: L | L11: Done | N11: C1
A12: 6.10b | B12: 6 Auth & authorization | C12: ApiFactory, AuthorizationTests, DbCollection | D12: WebApplicationFactory<Program> with Testing environment, pos_test DB, seeded owner, cashier, outsider (no membership), Other Shop; 6 authorization tests. | E12: Proves denial paths end-to-end, a guide requirement. | F12: dotnet test shows 11 passed. | G12: v1.0 | H12: P0 Critical | I12: Test | J12: 6.10 | K12: M | L12: Done | N12: C1
A13: 6.11a | B13: 6 Auth & authorization | C13: RefreshToken entity, DbContext mapping, migration AddRefreshTokens | D13: Token hash (SHA-256), FamilyId, UsedAt, RevokedAt, ExpiresAt, SessionStartedAt; unique hash index. | E13: Short access tokens need a safe renewal path; hashing means a database leak does not leak sessions. | F13: Migration applied; table exists. | G13: v1.0 | H13: P0 Critical | I13: DB | J13: 6.10 | K13: S | L13: Done | N13: C1
A14: 6.11b | B14: 6 Auth & authorization | C14: RefreshTokenService and TokenService options | D14: Issue, rotate (atomic consume with ExecuteUpdateAsync), revoke family on reuse, 14-day sliding with 30-day cap, re-check membership and lockout on refresh. | E14: Rotation plus reuse detection stops stolen-token replay. | F14: Reusing an old token revokes the whole family. | G14: v1.0 | H14: P0 Critical | I14: API | J14: 6.11a | K14: L | L14: Done | N14: C1
... A21: 6.12d | B21: 6 Auth & authorization | C21: PlatformAdminSeeder + user-secrets | D21: Create first platform admin from Seed:PlatformAdminEmail/Password (prompted into user-secrets); never promote an existing user. | E21: No hard-coded credentials and no accidental privilege escalation. | F21: Admin exists after first run only in Development. | G21: v1.0 | H21: P1 High | I21: API | J21: 6.12a | K21: S | L21: Pending | N21: H1
A22: 6.12e | B22: 6 Auth & authorization | C22: Platform endpoints | D22: POST /platform/auth/login, GET/POST /platform/tenants, GET /platform/audit. | E22: Lets you create tenants without SQL; replaces dev-only endpoints. | F22: Platform admin creates a tenant; list shows it. | G22: v1.0 | H22: P0 Critical | I22: API | J22: 6.12c | K22: M | L22: In progress | M22: PlatformEndpoints.cs built; waiting for 23/23 test result | N22: C1
A23: 6.12f | B23: 6 Auth & authorization | C23: PlatformAdminTests (6 tests) | D23: Platform admin cannot read tenant products; tenant owner cannot call platform endpoints; revoked flag denied; platform token has no tid. | E23: Proves the separation. | F23: dotnet test shows 23 passed. | G23: v1.0 | H23: P1 High | I23: Test | J23: 6.12e | K23: M | L23: Pending | N23: H1
A24: 6.13a | B24: 6 Auth & authorization | C24: AuthAuditEvent entity and migration AddPlatformAdminAndAudit | D24: AuthAuditEvents table (no FK to users), DbContext mapping using parameter b; migration also adds IsPlatformAdmin column. | E24: Audit rows must survive user deletion. | F24: Migration applied; flag column and table exist. | G24: v1.0 | H24: P1 High | I24: DB | J24: 6.12a | K24: M | L24: Pending | N24: H1
A25: 6.13b | B25: 6 Auth & authorization | C25: AuditLog service | D25: Records login success/failure, lockout, refresh reuse, refresh denied; write failure never breaks the request. | E25: Security events are needed to investigate abuse. | F25: Events visible in table after tests. | G25: v1.0 | H25: P1 High | I25: API | J25: 6.13a | K25: M | L25: Pending | N25: H1
A26: 6.13c | B26: 6 Auth & authorization | C26: Rate limiting on auth endpoints | D26: Fixed window policy 'auth', default 10/min per IP, RateLimit:AuthPermitPerMinute read at request time. | E26: Slows password guessing beyond lockout. | F26: 11th request in a minute returns 429. | G26: v1.0 | H26: P0 Critical | I26: API | J26: 6.12e | K26: S | L26: Pending | N26: C1
A27: 6.13d | B27: 6 Auth & authorization | C27: Security headers, HSTS, CORS from config, Cache-Control no-store | D27: Replace Program.cs and AuthEndpoints.cs; Cors:Origins list; HSTS outside Development. | E27: Browser-side hardening and safe configuration per environment. | F27: Response headers present on a request. | G27: v1.0 | H27: P0 Critical | I27: API | J27: 6.13c | K27: M | L27: In progress | M27: Program.cs given (CORS from config, headers, HSTS); no AuthEndpoints change needed (no-store is middleware) | N27: C1
A28: 6.13e | B28: 6 Auth & authorization | C28: HardeningTests (5 tests) | D28: Audit written, headers, no-store, CORS origins, rate limit. | E28: Locks hardening in. | F28: dotnet test shows 28 passed. | G28: v1.0 | H28: P1 High | I28: Test | J28: 6.13d | K28: M | L28: Pending | N28: H1
A29: 6.14 | B29: 6 Auth & authorization | C29: Step 6 sign-off | D29: All 28 tests pass; manual check: user can sign in, user without membership cannot query products; commit; git tag step-6-complete. | E29: Guide check for Step 6. | F29: Tag exists. | G29: v1.0 | H29: P1 High | I29: Process | J29: 6.13e | K29: S | L29: Pending | N29: H1
A30: 6.15 | B30: 6 Auth & authorization | C30: Sales endpoints: no-membership denial test | D30: When /sales exists, add test that a user without membership gets 403 and cannot read sales. | E30: Guide check lists sales explicitly. | F30: Test green (done with 9.19/11.3). | G30: v1.0 | H30: P0 Critical | I30: Test | J30: 9.4 | K30: S | L30: Pending | N30: C4
A31: 6.16 | B31: 6 Auth & authorization | C31: Forwarded headers for real client IP | D31: UseForwardedHeaders with known proxy; rate limit and audit use real IP. | E31: Behind a proxy every client looks like one IP. | F31: Audit shows client IP. | G31: v1.0 | H31: P1 High | I31: API | J31: 16.2 | K31: S | L31: Pending | N31: H1
A32: 6.17 | B32: 6 Auth & authorization | C32: Append-only audit permissions | D32: Database role without UPDATE/DELETE on AuthAuditEvents; retention policy documented. | E32: Prevents tampering with logs. | F32: App role cannot delete audit rows. | G32: v1.0 | H32: P2 Medium | I32: Ops | J32: 16.4 | K32: S | L32: Pending | N32: M1
A33: 6.18 | B33: 6 Auth & authorization | C33: Platform admin MFA (TOTP) | D33: Require TOTP on /platform/auth/login. Required before production. | E33: Platform admin controls every tenant. | F33: Login needs 6-digit code. | G33: v1.2 | H33: P1 High | I33: API | J33: 6.12e | K33: M | L33: Pending | N33: H1
A34: 6.19 | B34: 6 Auth & authorization | C34: Support sessions | D34: Time-limited, audited, owner-consented access to a tenant's data for support. | E34: Support without sharing passwords. | F34: Every session in audit. | G34: v2.0 | H34: P4 Low | I34: API | J34: 6.18 | K34: L | L34: Pending | N34: L1
A35: 6.20 | B35: 6 Auth & authorization | C35: Refresh token cleanup job | D35: Scheduled deletion of expired/revoked tokens. | E35: Table grows forever otherwise. | F35: Job removes old rows. | G35: v1.2 | H35: P3 Normal | I35: Ops | J35: 6.11b | K35: S | L35: Pending | N35: N1
A36: 6.21 | B36: 6 Auth & authorization | C36: PostgreSQL Row-Level Security | D36: Policy using app.tenant_id set per connection; app role must not own tables. | E36: Second isolation layer under the EF filter. | F36: Raw query without tenant returns nothing. | G36: v2.0 | H36: P2 Medium | I36: DB | J36: 7.17 | K36: L | L36: Pending | N36: M1
A37: 7.1 | B37: 7 Data model | C37: Branch entity + default branch | D37: Branches(Id, TenantId, Name, Code, Address, Phone, IsActive). Seed one 'Main' branch for Demo Shop. Composite unique (TenantId, Code). | E37: Sales and stock are per location; adding it later means rewriting every sales/stock row. | F37: Migration applied; Demo Shop has 1 branch; query filter hides other tenants' branches. | G37: v1.0 | H37: P0 Critical | I37: DB | J37: 6.12e | K37: S | L37: Pending | N37: C2
A38: 7.2 | B38: 7 Data model | C38: Category entity | D38: Categories(Id, TenantId, Name, ParentId nullable, IsActive). Unique (TenantId, Name). | E38: Products need grouping for the POS screen and reports. | F38: Table exists with tenant filter and unique index. | G38: v1.0 | H38: P0 Critical | I38: DB | J38: 6.12e | K38: S | L38: Pending | N38: C2
A39: 7.3 | B39: 7 Data model | C39: Extend Product | D39: Add CategoryId, Sku, Barcode, Price (numeric(18,2)), CostPrice, TaxRate (default 0), TrackStock bool, ReorderLevel (numeric(18,3)), UnitOfMeasure (piece, kg, litre, ...; default piece), IsActive, CreatedAtUtc, UpdatedAtUtc, RowVersion. Unique (TenantId, Sku) and (TenantId, Barcode) where not null. Composite FK (TenantId, CategoryId) to Categories. | E39: Composite FK makes cross-tenant category references impossible at database level. Decimal money avoids rounding bugs. A unit of measure is needed because shops sell sugar, rice and oil by weight or volume. | F39: Inserting a product pointing at another tenant's category fails in the database. | G39: v1.0 | H39: P0 Critical | I39: DB | J39: 7.2 | K39: M | L39: Pending | N39: C2
... A51: 7.15 | B51: 7 Data model | C51: Tenant keys and audit columns on every new table | D51: Every new table carries TenantId and a composite FK to its parent (TenantId, ParentId), not just ParentId. All business tables get CreatedAtUtc and CreatedByUserId; master data also UpdatedAtUtc. Money numeric(18,2), quantities numeric(18,3), times in UTC. | E51: A payment or sale line must not be able to point at another shop's sale or product even through a coding mistake. Consistent columns make audit and reports simpler. | F51: Review of the generated SQL (7.17) shows no table with a single-column FK to a tenant-owned parent. | G51: v1.0 | H51: P0 Critical | I51: DB | J51: 7.4, 7.5, 7.6 | K51: S | L51: Pending | N51: C2
A52: 7.16 | B52: 7 Data model | C52: Report indexes and demo seed data | D52: Index Sales (TenantId, BranchId, BusinessDate) and (TenantId, BranchId, CreatedAtUtc); Payments (TenantId, SaleId); StockMovements (TenantId, ProductId, CreatedAtUtc). Seed for Demo Shop: Main branch, default terminal, 'General' category, 5 sample products with opening stock. | E52: History and report screens always filter by tenant, branch and date, so those indexes are needed from the start. Sample data lets the first screens show something. | F52: EXPLAIN on the daily-sales query uses the index; Demo Shop lists sample products. | G52: v1.0 | H52: P2 Medium | I52: DB | J52: 7.4, 7.6 | K52: S | L52: Pending | M52: Own migration when built. | N52: M1
A53: 7.17 | B53: 7 Data model | C53: Migration AddCoreDataModel + review SQL | D53: One migration (AddCoreDataModel) for the critical tables 7.1-7.6, 7.11-7.13 and 7.15. Review the generated SQL before applying (dotnet ef migrations script): numeric not double, composite FKs and unique indexes present, no single-column FK to a tenant-owned parent. Tables from 7.7-7.10, 7.14 and 7.16 get their own small migration when their slice is built. | E53: Reading the SQL catches wrong types (e.g. double instead of numeric) before data exists. | F53: dotnet ef database update succeeds; \dt in psql shows the critical tables; app still starts and all tests pass. | G53: v1.0 | H53: P0 Critical | I53: DB | J53: 7.1-7.6, 7.11, 7.12, 7.13, 7.15 | K53: S | L53: Pending | N53: C2
A54: 8.1 | B54: 8 Products & categories | C54: Category API | D54: GET /categories, POST, PUT /{id}, DELETE (soft: IsActive=false). Permissions: products.read / products.write. | E54: Category must exist before products can be organised. | F54: All endpoints return 401/403/404 correctly; tenant filter applied. | G54: v1.0 | H54: P1 High | I54: API | J54: 7.2 | K54: M | L54: Pending | N54: H2
A55: 8.2 | B55: 8 Products & categories | C55: Product API: list with paging, search, filter | D55: GET /products?search=&categoryId=&page=&pageSize=&active= returning {items,total}. Search by name, SKU, barcode (case-insensitive, indexed). Max pageSize 100. | E55: Never load every product; shops can have thousands of SKUs. | F55: Searching 'sug' returns sugar; page 2 returns next items. | G55: v1.0 | H55: P0 Critical | I55: API | J55: 7.3 | K55: M | L55: Pending | N55: C3
A56: 8.3 | B56: 8 Products & categories | C56: Product API: create, update, deactivate | D56: POST/PUT/DELETE(soft). Server validation: name required, price >= 0, 2 decimals, SKU/barcode unique per tenant, category belongs to tenant, concurrency via RowVersion (409 on conflict). Return ProblemDetails with field errors. | E56: Server is the only trusted validator; frontend rules are convenience. | F56: Duplicate SKU returns 409/400 with clear message; other tenant's category ID returns 404. | G56: v1.0 | H56: P0 Critical | I56: API | J56: 8.2 | K56: M | L56: Pending | N56: C3
A57: 8.4 | B57: 8 Products & categories | C57: Price change audit | D57: Write AuditLogs row (old price, new price, user) when price changes. | E57: Detects staff price tampering. | F57: Audit row appears after PUT with new price. | G57: v1.0 | H57: P2 Medium | I57: API | J57: 7.7, 8.3 | K57: S | L57: Pending | N57: M1
A58: 8.5 | B58: 8 Products & categories | C58: Opening stock on product create | D58: Optional OpeningQuantity creates a StockMovement(Reason=Opening) for the user's branch. | E58: Lets owner load existing shop stock without a separate step. | F58: On-hand equals opening quantity. | G58: v1.0 | H58: P0 Critical | I58: API | J58: 7.6, 8.3 | K58: S | L58: Pending | N58: C3
A59: 8.6 | B59: 8 Products & categories | C59: Barcode lookup endpoint | D59: GET /products/by-barcode/{code}. | E59: Barcode scanner types digits + Enter; need instant exact lookup. | F59: Returns product or 404 in under 100 ms locally. | G59: v1.0 | H59: P1 High | I59: API | J59: 8.3 | K59: S | L59: Pending | N59: H2
A60: 8.7 | B60: 8 Products & categories | C60: Frontend: product list page | D60: Table with search box (debounced), category filter, pagination, active toggle, loading/empty/error states, low-stock badge. | E60: Daily-use screen for owner/stock controller. | F60: Refresh page keeps data from DB; empty state shows 'Add your first product'. | G60: v1.0 | H60: P0 Critical | I60: Frontend | J60: 8.2 | K60: M | L60: Pending | N60: C5
A61: 8.8 | B61: 8 Products & categories | C61: Frontend: product form | D61: Create/edit form with inline validation errors from server, price formatting (KES), category picker, save/cancel, prevents double submit. | E61: Reduces data-entry errors. | F61: Added product visible after refresh; validation message shown for duplicate SKU. | G61: v1.0 | H61: P0 Critical | I61: Frontend | J61: 8.3 | K61: M | L61: Pending | N61: C5
A62: 8.9 | B62: 8 Products & categories | C62: Frontend: category management | D62: Simple list + add/rename/deactivate dialog. | E62: Needed for the POS category filter. | F62: Category appears in product form dropdown. | G62: v1.0 | H62: P2 Medium | I62: Frontend | J62: 8.1 | K62: S | L62: Pending | N62: M2
A63: 8.10 | B63: 8 Products & categories | C63: Tenant isolation tests for products/categories | D63: Tests: tenant A cannot get, update, delete or list tenant B's products/categories; cashier cannot POST. | E63: Guide completion check for Step 8. | F63: Tests green and included in dotnet test. | G63: v1.0 | H63: P0 Critical | I63: Test | J63: 8.3 | K63: M | L63: Pending | N63: C3
A64: 8.11 | B64: 8 Products & categories | C64: Bulk import products from CSV | D64: Upload CSV (name, sku, barcode, price, category, opening qty), validate rows, report errors per line, insert in one transaction. | E64: Real shops have hundreds of items; typing them is the biggest adoption barrier. | F64: Import of 200 rows works; bad rows reported without partial insert. | G64: v1.1 | H64: P2 Medium | I64: API+Frontend | J64: 8.3 | K64: L | L64: Pending | N64: M2
... A67: 9.1 | B67: 9 Checkout & stock ledger | C67: Pricing and rounding rules (domain class) | D67: Pure C# class SaleCalculator: line total = round(qty*price - discount, 2, MidpointRounding.AwayFromZero); tax handling (inclusive/exclusive setting per tenant); totals from lines. No EF or HTTP inside. | E67: Money logic must be unit-testable and identical everywhere. | F67: Unit tests for rounding, discount, tax, zero qty pass. | G67: v1.0 | H67: P0 Critical | I67: Domain | J67: 7.4 | K67: M | L67: Pending | N67: C4
A68: 9.2 | B68: 9 Checkout & stock ledger | C68: Tenant settings (currency, tax, receipt header) | D68: TenantSettings: CurrencyCode (KES), TaxInclusive, DefaultTaxRate, BusinessName, Address, Phone, receipt footer, TaxPIN optional. | E68: Receipts and totals depend on them. | F68: GET/PUT /settings (owner only). | G68: v1.0 | H68: P1 High | I68: DB+API | J68: 7.1 | K68: S | L68: Pending | M68: Table is created in 7.12; this step adds the GET/PUT endpoints. | N68: H2
A69: 9.3 | B69: 9 Checkout & stock ledger | C69: Receipt numbering | D69: Per branch sequential ReceiptNo generated server-side in the transaction (e.g. MAIN-000123) using a counter row with lock. | E69: Shops need readable, gap-free receipt numbers; UUID is not human friendly. | F69: Two concurrent sales never share a number. | G69: v1.0 | H69: P0 Critical | I69: API | J69: 7.4 | K69: M | L69: Pending | M69: Counter table is created in 7.13; this step adds the numbering logic. | N69: C4
A70: 9.4 | B70: 9 Checkout & stock ledger | C70: POST /sales (checkout) in one transaction | D70: Request: saleId (client UUID), branchId, items[{productId, quantity}], payments[{method, amount, reference}]. Server re-reads prices from DB, validates product active/belongs to tenant, qty > 0, branch belongs to user's membership, payment >= total. Creates Sale, SaleItems, Payments, StockMovements(-qty) atomically. | E70: Never trust browser totals. A single transaction means no half-saved sale. | F70: Forced failure mid-way leaves zero rows in all tables. | G70: v1.0 | H70: P0 Critical | I70: API | J70: 9.1, 9.3, 7.4-7.6, 7.11, 7.13 | K70: L | L70: Pending | M70: No stock check until 9.6 (negative stock policy); stock ledger and StockLevels are updated in the same transaction. | N70: C4
A71: 9.5 | B71: 9 Checkout & stock ledger | C71: Idempotent sale submission | D71: If saleId already exists for tenant, return the stored sale (200) rather than creating another. Unique index on (TenantId, Id). | E71: Network retries and later offline sync must not duplicate sales. | F71: Posting same saleId twice yields one sale and one set of stock movements. | G71: v1.0 | H71: P0 Critical | I71: API | J71: 9.4 | K71: S | L71: Pending | N71: C4
A72: 9.6 | B72: 9 Checkout & stock ledger | C72: Negative stock policy | D72: Tenant setting AllowNegativeStock (default false). If false and on-hand < qty, return 409 listing products. Use row lock / serializable check on product stock during checkout. | E72: Prevents overselling; shop decides strictness. | F72: Selling more than on-hand is rejected when setting is off. | G72: v1.0 | H72: P1 High | I72: API | J72: 9.4 | K72: M | L72: Pending | N72: H2
A73: 9.7 | B73: 9 Checkout & stock ledger | C73: Cash payment, change due | D73: Cash tendered vs total; change = tendered - total, stored on Payment. | E73: Cashier needs change figure on screen and receipt. | F73: Receipt shows tendered and change. | G73: v1.0 | H73: P0 Critical | I73: API | J73: 9.4 | K73: S | L73: Pending | N73: C4
A74: 9.8 | B74: 9 Checkout & stock ledger | C74: M-Pesa (manual reference) and other payment methods | D74: Accept method=Mpesa with transaction code reference (validated format, unique per tenant), split payments (cash + M-Pesa). No live API call in v1.0. | E74: Most Kenyan retail takes M-Pesa; recording the code gives reconciliation without integration risk. | F74: Sale with Mpesa reference saved; duplicate reference rejected. | G74: v1.0 | H74: P0 Critical | I74: API | J74: 9.4 | K74: M | L74: Pending | N74: C4
A75: 9.9 | B75: 9 Checkout & stock ledger | C75: Discounts | D75: Per-line and per-sale discount (amount or %), permission sales.discount, max % per role, audit entry. | E75: Common POS need; permission-gated to prevent abuse. | F75: Cashier over limit is denied; manager allowed. | G75: v1.1 | H75: P2 Medium | I75: API | J75: 9.4 | K75: M | L75: Pending | N75: M2
A76: 9.10 | B76: 9 Checkout & stock ledger | C76: Sales history API | D76: GET /sales?from=&to=&branchId=&cashierId=&page=; GET /sales/{id} with items and payments. Cashier sees only own sales unless permission sales.read.all. | E76: Owner reviews the day; guide requires history. | F76: Sale appears once; other tenant's sale is 404. | G76: v1.0 | H76: P1 High | I76: API | J76: 9.4 | K76: M | L76: Pending | N76: H2
A77: 9.11 | B77: 9 Checkout & stock ledger | C77: Void sale | D77: POST /sales/{id}/void with reason; permission sales.void; sets Status=Voided and adds reversing StockMovements(+qty, Reason=Void); never deletes rows. | E77: Mistakes happen; ledger must stay traceable. | F77: Stock restored; audit row; second void rejected. | G77: v1.0 | H77: P1 High | I77: API | J77: 9.10 | K77: M | L77: Pending | N77: H2
A78: 9.12 | B78: 9 Checkout & stock ledger | C78: Returns / refunds | D78: Return items against a sale: reversing stock movements, refund payment record, limit to sold quantity. | E78: Customers return goods; needed within weeks of real use. | F78: Cannot return more than sold. | G78: v1.1 | H78: P2 Medium | I78: API | J78: 9.10 | K78: L | L78: Pending | N78: M2
A79: 9.13 | B79: 9 Checkout & stock ledger | C79: Stock receiving (purchases-lite) | D79: POST /stock/receive {branchId, items[{productId, qty, unitCost}], supplierName?, note} creates StockMovements(Receive) and updates cost price optionally. Permission stock.write. | E79: Without receiving, stock only goes down and shows wrong numbers. | F79: On-hand increases; audit written. | G79: v1.0 | H79: P1 High | I79: API | J79: 7.6 | K79: M | L79: Pending | N79: H3
A80: 9.14 | B80: 9 Checkout & stock ledger | C80: Stock adjustment (count correction, damage) | D80: POST /stock/adjust with reason (Damage, Expired, CountCorrection) and mandatory note. | E80: Physical stock rarely matches system. | F80: Adjustment row visible in movement history. | G80: v1.0 | H80: P1 High | I80: API | J80: 7.6 | K80: S | L80: Pending | N80: H3
A81: 9.15 | B81: 9 Checkout & stock ledger | C81: Stock levels and movement history API | D81: GET /stock?branchId= (on-hand, reorder flag), GET /stock/{productId}/movements. | E81: Stock controller needs to see what is low and why. | F81: Totals match sum of ledger. | G81: v1.0 | H81: P1 High | I81: API | J81: 7.6 | K81: M | L81: Pending | N81: H3
A82: 9.16 | B82: 9 Checkout & stock ledger | C82: Reports: daily totals | D82: GET /reports/daily?date=&branchId= returning sales count, gross, discounts, tax, totals by payment method, voids, top 10 products. | E82: Guide requires a simple daily report; shop closes the day with it. | F82: Numbers match manual sum of sales. | G82: v1.0 | H82: P1 High | I82: API | J82: 9.10 | K82: M | L82: Pending | N82: H4
... A89: 10.4 | B89: 10 End-to-end workflow | C89: Load /me, tenant, branch selection | D89: After login fetch user, tenant name, permissions, allowed branches; store selected branch (persist per device). | E89: POS must know the branch before selling. | F89: Header shows shop and branch names. | G89: v1.0 | H89: P0 Critical | I89: Frontend+API | J89: 10.2, 7.1 | K89: M | L89: Pending | N89: C5
A90: 10.5 | B90: 10 End-to-end workflow | C90: POS sale screen | D90: Product search/barcode input (Enter adds item), category tiles, cart with +/- quantity and remove, live totals, hold/clear cart, keyboard shortcuts. | E90: Core cashier workflow; speed matters. | F90: Cashier can build a 5-item cart in under 30 seconds. | G90: v1.0 | H90: P0 Critical | I90: Frontend | J90: 10.3 | K90: L | L90: Pending | M90: Search by name first; barcode scan (8.6) is added in slice H2. | N90: C5
A91: 10.6 | B91: 10 End-to-end workflow | C91: Payment dialog | D91: Cash/M-Pesa/split, tendered amount, change due, reference input; generates saleId UUID before sending; disables button while submitting. | E91: Client UUID + disabled button prevents duplicates. | F91: Completed sale appears once in history. | G91: v1.0 | H91: P0 Critical | I91: Frontend | J91: 9.4, 10.5 | K91: M | L91: Pending | N91: C5
A92: 10.7 | B92: 10 End-to-end workflow | C92: Receipt view and print | D92: Receipt component (shop header, items, totals, payment, receipt no, cashier, footer), browser print CSS for 58/80 mm thermal paper, reprint from history. | E92: Customers expect a receipt. | F92: Print preview fits 80 mm width. | G92: v1.0 | H92: P0 Critical | I92: Frontend | J92: 10.6 | K92: M | L92: Pending | M92: Uses default KES and generic header until 9.2 (settings endpoints) is built. | N92: C5
A93: 10.8 | B93: 10 End-to-end workflow | C93: Sales history screen | D93: Date range, cashier filter, list with totals, detail drawer, void button (permission-gated). | E93: Owner/manager review. | F93: Void changes status and stock. | G93: v1.0 | H93: P1 High | I93: Frontend | J93: 9.10 | K93: M | L93: Pending | N93: H2
A94: 10.9 | B94: 10 End-to-end workflow | C94: Daily report screen | D94: Date picker, totals cards, payment method breakdown, top products, print. | E94: Closing the day. | F94: Matches API report. | G94: v1.0 | H94: P1 High | I94: Frontend | J94: 9.16 | K94: M | L94: Pending | N94: H4
A95: 10.10 | B95: 10 End-to-end workflow | C95: Stock screens | D95: Stock levels with low-stock filter, receive stock form, adjustment form, movement history. | E95: Stock controller workflow. | F95: Receiving updates on-hand immediately. | G95: v1.0 | H95: P1 High | I95: Frontend | J95: 9.13-9.15 | K95: L | L95: Pending | N95: H3
A96: 10.11 | B96: 10 End-to-end workflow | C96: User management (owner) | D96: Owner invites/creates staff user in own tenant, assigns role, deactivates membership, resets password (temporary password forced change). API: /users, /users/{id}/role, /users/{id}/deactivate. | E96: Owner cannot onboard cashiers without it; today only seeded users exist. | F96: New cashier can sign in; deactivated cashier is denied at next request. | G96: v1.0 | H96: P1 High | I96: API+Frontend | J96: 6.14 | K96: L | L96: Pending | N96: H4
A97: 10.12 | B97: 10 End-to-end workflow | C97: Change own password / forced change | D97: POST /auth/change-password; revoke all refresh tokens afterwards. | E97: Basic account hygiene. | F97: Old password stops working. | G97: v1.0 | H97: P2 Medium | I97: API+Frontend | J97: 6.11c | K97: S | L97: Pending | N97: M2
A98: 10.13 | B98: 10 End-to-end workflow | C98: Password reset by email | D98: Reset link via email provider, token expiry, rate limit. | E98: Needs email infrastructure; owner can reset staff passwords in v1.0. | F98: Reset email arrives and works once. | G98: v1.2 | H98: P3 Normal | I98: API | J98: 10.11 | K98: M | L98: Pending | N98: N1
A99: 10.14 | B99: 10 End-to-end workflow | C99: Global error and empty states, toasts | D99: Consistent loading spinners, error boundary, toast messages. | E99: Usability baseline. | F99: No unhandled blank screens. | G99: v1.0 | H99: P2 Medium | I99: Frontend | J99: 10.1 | K99: S | L99: Pending | N99: M2
A100: 10.15 | B100: 10 End-to-end workflow | C100: Environment config and narrow CORS | D100: Cors:Origins set to the frontend URL only; VITE_API_URL in .env files; no secrets in frontend. | E100: Guide requirement. | F100: Request from another origin is blocked. | G100: v1.0 | H100: P1 High | I100: Config | J100: 6.13d | K100: S | L100: Pending | N100: H4
A101: 10.16 | B101: 10 End-to-end workflow | C101: Milestone check: complete one sale in browser | D101: Manual script: sign in, add product, sell it, view receipt, see sale in history and row in PostgreSQL. | E101: Guide milestone for Step 10. | F101: Checklist signed off. | G101: v1.0 | H101: P0 Critical | I101: Test | J101: 10.1-10.7 | K101: S | L101: Pending | N101: C5
A102: 11.1 | B102: 11 Tests | C102: Domain unit tests (xUnit) | D102: Calculator, discount, tax, rounding, stock rules. | E102: Pure logic is cheapest to test. | F102: Green with at least 25 cases. | G102: v1.0 | H102: P0 Critical | I102: Test | J102: 9.1 | K102: M | L102: Pending | N102: C4
A103: 11.2 | B103: 11 Tests | C103: API integration tests on pos_test database | D103: WebApplicationFactory; tests for product CRUD, checkout atomicity, idempotency, validation, auth and permissions. | E103: Catches regressions across layers. | F103: Suite runs from dotnet test. | G103: v1.0 | H103: P0 Critical | I103: Test | J103: 9.19 | K103: L | L103: Pending | N103: C4
A104: 11.3 | B104: 11 Tests | C104: Tenant isolation test matrix | D104: Generated tests across every tenant-owned endpoint: A cannot list/get/update/delete B's records; user without membership gets 403. | E104: Guide's non-negotiable. | F104: Every endpoint appears in the matrix. | G104: v1.0 | H104: P0 Critical | I104: Test | J104: 8.10, 9.4 | K104: L | L104: Pending | N104: C4
... A152: 16.9 | B152: 16 Release & operations (added) | C152: Basic analytics and exports | D152: Date-range sales, product, stock-valuation reports with CSV export. | E152: Owners ask for exports quickly. | F152: CSV opens correctly in Excel. | G152: v1.2 | H152: P2 Medium | I152: API+Frontend | J152: 9.16 | K152: M | L152: Pending | N152: M5

Sheet Versions
A1: Version | B1: Name | C1: Goal | D1: Ships when | E1: Tasks | F1: Critical tasks | G1: Done | H1: % done
A2: v1.0 | B2: Online POS - first usable release | C2: Tenant-safe sign-in, products/categories, cash + M-Pesa-reference checkout, receipts, sales history, stock ledger (receive/adjust), daily report, staff management, backups, deployed and piloted in one shop. | D2: One real shop sells for a week with no data loss; isolation and checkout tests green. | E2: =COUNTIF('Roadmap 6-16'!$G$2:$G$152,A2) -> 105 | F2: =COUNTIFS('Roadmap 6-16'!$G$2:$G$152,A2,'Roadmap 6-16'!$H$2:$H$152,"P0 Critical") -> 63 | G2: =COUNTIFS('Roadmap 6-16'!$G$2:$G$152,A2,'Roadmap 6-16'!$L$2:$L$152,"Done") -> 19 | H2: =IF(E2=0,0,G2/E2) -> 0.18095238
A3: v1.1 | B3: Offline single device + sync | C3: PWA install, local catalogue, offline checkout, safe idempotent sync, conflict flags, CSV product import, discounts, returns. | D3: Sell offline on one device per branch and sync with zero duplicates. | E3: =COUNTIF('Roadmap 6-16'!$G$2:$G$152,A3) -> 24 | F3: =COUNTIFS('Roadmap 6-16'!$G$2:$G$152,A3,'Roadmap 6-16'!$H$2:$H$152,"P0 Critical") -> 0 | G3: =COUNTIFS('Roadmap 6-16'!$G$2:$G$152,A3,'Roadmap 6-16'!$L$2:$L$152,"Done") -> 0 | H3: =IF(E3=0,0,G3/E3) -> 0
A4: v1.2 | B4: SaaS operations | C4: Tenant onboarding, plans/trials, manual billing, platform dashboard and MFA, shifts, exports, monitoring, Swahili. | D4: You can onboard and manage several shops without touching the database. | E4: =COUNTIF('Roadmap 6-16'!$G$2:$G$152,A4) -> 13 | F4: =COUNTIFS('Roadmap 6-16'!$G$2:$G$152,A4,'Roadmap 6-16'!$H$2:$H$152,"P0 Critical") -> 0 | G4: =COUNTIFS('Roadmap 6-16'!$G$2:$G$152,A4,'Roadmap 6-16'!$L$2:$L$152,"Done") -> 0 | H4: =IF(E4=0,0,G4/E4) -> 0
A5: v2.0 | B5: Scale and compliance | C5: RLS, automated billing, multi-terminal offline, suppliers/POs, variants, images, support sessions, eTIMS review, dedicated installs. | D5: Chosen per customer demand. | E5: =COUNTIF('Roadmap 6-16'!$G$2:$G$152,A5) -> 9 | F5: =COUNTIFS('Roadmap 6-16'!$G$2:$G$152,A5,'Roadmap 6-16'!$H$2:$H$152,"P0 Critical") -> 0 | G5: =COUNTIFS('Roadmap 6-16'!$G$2:$G$152,A5,'Roadmap 6-16'!$L$2:$L$152,"Done") -> 0 | H5: =IF(E5=0,0,G5/E5) -> 0
A8: Priority = how important a task is; Version = when it ships. They are independent. Filter Priority = P0 Critical to see what must exist for the app to be safe and correct.
A10: Priority | B10: Meaning | C10: Examples | D10: Tasks | E10: v1.0 | F10: v1.1 | G10: v1.2 | H10: v2.0
A11: P0 Critical | B11: Must be in place. The app is unsafe or wrong without it. | C11: Tenant isolation, sign-in, rate limiting, money maths, checkout, stock ledger, backups | D11: =COUNTIF('Roadmap 6-16'!$H$2:$H$152,A11) -> 63 | E11: =COUNTIFS('Roadmap 6-16'!$H$2:$H$152,$A11,'Roadmap 6-16'!$G$2:$G$152,"v1.0") -> 63 | F11: =COUNTIFS('Roadmap 6-16'!$H$2:$H$152,$A11,'Roadmap 6-16'!$G$2:$G$152,"v1.1") -> 0 | G11: =COUNTIFS('Roadmap 6-16'!$H$2:$H$152,$A11,'Roadmap 6-16'!$G$2:$G$152,"v1.2") -> 0 | H11: =COUNTIFS('Roadmap 6-16'!$H$2:$H$152,$A11,'Roadmap 6-16'!$G$2:$G$152,"v2.0") -> 0
A12: P1 High | B12: Very important. Needed for real daily use of the shop. | C12: Audit log, daily reports, stock receiving, offline sync, tenant onboarding | D12: =COUNTIF('Roadmap 6-16'!$H$2:$H$152,A12) -> 45 | E12: =COUNTIFS('Roadmap 6-16'!$H$2:$H$152,$A12,'Roadmap 6-16'!$G$2:$G$152,"v1.0") -> 27 | F12: =COUNTIFS('Roadmap 6-16'!$H$2:$H$152,$A12,'Roadmap 6-16'!$G$2:$G$152,"v1.1") -> 14 | G12: =COUNTIFS('Roadmap 6-16'!$H$2:$H$152,$A12,'Roadmap 6-16'!$G$2:$G$152,"v1.2") -> 3 | H12: =COUNTIFS('Roadmap 6-16'!$H$2:$H$152,$A12,'Roadmap 6-16'!$G$2:$G$152,"v2.0") -> 1
A13: P2 Medium | B13: Important. Makes the app good, but a shop can start without it. | C13: Price-change audit, CSV import, shifts, CI pipeline | D13: =COUNTIF('Roadmap 6-16'!$H$2:$H$152,A13) -> 29 | E13: =COUNTIFS('Roadmap 6-16'!$H$2:$H$152,$A13,'Roadmap 6-16'!$G$2:$G$152,"v1.0") -> 12 | F13: =COUNTIFS('Roadmap 6-16'!$H$2:$H$152,$A13,'Roadmap 6-16'!$G$2:$G$152,"v1.1") -> 10 | G13: =COUNTIFS('Roadmap 6-16'!$H$2:$H$152,$A13,'Roadmap 6-16'!$G$2:$G$152,"v1.2") -> 6 | H13: =COUNTIFS('Roadmap 6-16'!$H$2:$H$152,$A13,'Roadmap 6-16'!$G$2:$G$152,"v2.0") -> 1
A14: P3 Normal | B14: Can be skipped now and added later. | C14: Password reset by email, Swahili UI, start script | D14: =COUNTIF('Roadmap 6-16'!$H$2:$H$152,A14) -> 8 | E14: =COUNTIFS('Roadmap 6-16'!$H$2:$H$152,$A14,'Roadmap 6-16'!$G$2:$G$152,"v1.0") -> 3 | F14: =COUNTIFS('Roadmap 6-16'!$H$2:$H$152,$A14,'Roadmap 6-16'!$G$2:$G$152,"v1.1") -> 0 | G14: =COUNTIFS('Roadmap 6-16'!$H$2:$H$152,$A14,'Roadmap 6-16'!$G$2:$G$152,"v1.2") -> 3 | H14: =COUNTIFS('Roadmap 6-16'!$H$2:$H$152,$A14,'Roadmap 6-16'!$G$2:$G$152,"v2.0") -> 2
A15: P4 Low | B15: Can do without. | C15: Product images, customers table, support sessions | D15: =COUNTIF('Roadmap 6-16'!$H$2:$H$152,A15) -> 6 | E15: =COUNTIFS('Roadmap 6-16'!$H$2:$H$152,$A15,'Roadmap 6-16'!$G$2:$G$152,"v1.0") -> 0 | F15: =COUNTIFS('Roadmap 6-16'!$H$2:$H$152,$A15,'Roadmap 6-16'!$G$2:$G$152,"v1.1") -> 0 | G15: =COUNTIFS('Roadmap 6-16'!$H$2:$H$152,$A15,'Roadmap 6-16'!$G$2:$G$152,"v1.2") -> 1 | H15: =COUNTIFS('Roadmap 6-16'!$H$2:$H$152,$A15,'Roadmap 6-16'!$G$2:$G$152,"v2.0") -> 5

Sheet Requirements
A1: # | B1: Requirement in the guide | C1: Where it is covered | D1: Status | E1: What exists / what is missing | F1: Next action
A2: 1 | B2: Tenant, User and TenantMembership with a tenant-specific role | C2: 6.1 to 6.5 | D2: Done | E2: Entities, Identity tables and migration are in place. | F2: None.
A3: 2 | B3: Roles: platform administrator, business owner, manager, cashier, stock controller | C3: 6.8, 6.12 | D3: Ready to build | E3: Four tenant roles are seeded. The platform administrator (separate sign-in, scope=platform token, no tenant data access) has full steps and code. | F3: Build 6.12a to 6.12f and pass PlatformAdminTests.
A4: 3 | B4: Tenant resolved from the validated authenticated context, never from a browser-sent TenantId | C4: 6.9 | D4: Done | E4: Tenant comes from the signed tid claim. The product create request has no tenant field. | F4: None.
A5: 4 | B5: Check permission and membership on every protected operation | C5: 6.10 | D5: Done | E5: Policy handler checks active membership, active tenant and role permission on /products and /me. Sales endpoints do not exist yet. | F5: Apply the same policies to sales endpoints when they are built.
A6: 5 | B6: Seed one development tenant and owner account; no hard-coded credentials | C6: 6.8 | D6: Done | E6: Owner and platform admin credentials come from user-secrets. Seeders run in Development only. | F6: None.
A7: 6 | B7: Tests that try to reach another tenant's records and expect denial | C7: 6.6, 6.10b | D7: Ready to build | E7: Isolation tests pass (5). The end-to-end authorization tests (6) are written; the test files still have to be added and run. | F7: Add ApiFactory, AuthorizationTests and DbCollection.
A8: 7 | B8: Check: users can sign in; a user without membership cannot query a tenant's products or sales | C8: 6.9, 6.10b | D8: Ready to build | E8: Sign-in works. The no-membership test for products is written, not yet run. Sales do not exist yet. | F8: Run the tests; add the sales version when sales endpoints exist.

Sheet Sub-steps
A1: Item | B1: Title | C1: Status | D1: Required by guide? | E1: Notes
A2: 6.1 | B2: Domain base types (ITenantOwned, TenantEntity) | C2: Done | D2: Yes
A3: 6.2 | B3: Permissions and system role entities | C3: Done | D3: Yes
A4: 6.3 | B4: Tenant, TenantMembership and Product entities | C4: Done | D4: Yes
A5: 6.4 | B5: Tenant context abstraction and AppUser | C5: Done | D5: Yes
A6: 6.5 | B6: AppDbContext: Identity, query filter and SaveChanges tenant rules | C6: Done | D6: Yes
A7: 6.6 | B7: Tenant-isolation tests | C7: Done | D7: Yes | E7: 5 tests passing when POS_TEST_CONNECTION is set.
A8: 6.7 | B8: Migration AddIdentityAndTenancy | C8: Done | D8: Yes | E8: Applied to pos_dev.
A9: 6.8 | B9: Seed roles, demo tenant and owner account | C9: Done | D9: Yes | E9: Credentials from user-secrets.
A10: 6.9 | B10: Sign-in endpoint, JWT with sub and tid claims, and /me | C10: Done | D10: Yes | E10: Lockout after 5 failed attempts for 15 minutes.
A11: 6.10 | B11: Permission policies, default-deny, product endpoints | C11: Done | D11: Yes | E11: Committed.
A12: 6.10b | B12: Add and run ApiFactory, AuthorizationTests and DbCollection | C12: Ready to build | D12: Yes | E12: Needs Microsoft.AspNetCore.Mvc.Testing in Pos.Tests.
A13: 6.11 | B13: Refresh tokens with rotation, reuse detection and logout (migration AddRefreshTokens, RefreshTokenTests) | C13: Ready to build | D13: Beyond guide | E13: HttpOnly cookie scoped to /auth, SameSite=Strict, hashed in the database.
A14: 6.12a | B14: AppUser.IsPlatformAdmin flag | C14: Ready to build | D14: Yes | E14: Part of migration AddPlatformAdminAndAudit.
A15: 6.12b | B15: TokenService: platform token (scope=platform, no tid, 10 minutes) | C15: Ready to build | D15: Yes | E15: Replace TokenService.cs.
A16: 6.12c | B16: Platform admin requirement and handler (policy platform.admin) | C16: Ready to build | D16: Yes | E16: Re-checks the database flag and lockout on every call.
A17: 6.12d | B17: PlatformAdminSeeder and user-secrets for platform admin | C17: Ready to build | D17: Yes | E17: Never promotes an existing user automatically.
A18: 6.12e | B18: Platform endpoints: /platform/auth/login, /platform/tenants, /platform/audit | C18: Ready to build | D18: Yes | E18: Replaces the removed /dev/tenants endpoints.
A19: 6.12f | B19: PlatformAdminTests (6 tests) | C19: Ready to build | D19: Yes | E19: Platform admin cannot read tenant products; tenant owner cannot use platform endpoints.
A20: 6.13a | B20: AuthAuditEvent entity, DbContext mapping and migration AddPlatformAdminAndAudit | C20: Ready to build | D20: Beyond guide
A21: 6.13b | B21: AuditLog service; audit refresh reuse and denial | C21: Ready to build | D21: Beyond guide | E21: A failed audit write never breaks the request.
A22: 6.13c | B22: Rate limiting on /auth/login, /auth/refresh and /platform/auth/login | C22: Ready to build | D22: Beyond guide | E22: 10 requests per minute per IP, configurable.
A23: 6.13d | B23: Security headers, HSTS outside Development, configurable CORS origins | C23: Ready to build | D23: Beyond guide | E23: Replace Program.cs, AuthEndpoints.cs; add PlatformEndpoints.cs.
A24: 6.13e | B24: HardeningTests (5 tests) | C24: Ready to build | D24: Beyond guide | E24: Audit, headers, no-store, CORS, rate limit.
A25: 6.14 | B25: Step 6 sign-off: all 28 tests pass, commit, tag step-6-complete | C25: Ready to build | D25: Yes | E25: git tag step-6-complete.
A26: Later | B26: No-membership test for sales endpoints | C26: Pending | D26: Yes | E26: Add when sales endpoints exist.
A27: Later | B27: MFA for the platform administrator | C27: Pending | D27: Before production | E27: Required before any production deployment.
A28: Later | B28: Support sessions: time-limited, audited access to a tenant's data | C28: Pending | D28: Beyond guide
A29: Later | B29: Forwarded headers so rate limiting and audit see the real client IP | C29: Pending | D29: Before production | E29: Needed behind a proxy.
A30: Later | B30: Append-only audit permissions and retention period | C30: Pending | D30: Before production | E30: Restrict UPDATE and DELETE on AuthAuditEvents for the app role.
A31: Later | B31: Cleanup job for expired refresh tokens | C31: Pending | D31: Beyond guide
A32: Later | B32: Frontend sign-in: in-memory access token and automatic refresh | C32: Pending | D32: Beyond guide | E32: Uses credentials: include and refresh on 401.
A33: Later | B33: PostgreSQL Row-Level Security as an extra tenant-isolation layer | C33: Pending | D33: Beyond guide | E33: App role must not own the tables.

Sheet Tests
A1: Test class | B1: What it proves | C1: Expected tests | D1: Status
A2: TenantIsolationTests | B2: Query filter and SaveChanges block cross-tenant reads and writes | C2: 5 | D2: Done
A3: AuthorizationTests | B3: No token, wrong role, no membership and another tenant's record are all denied | C3: 6 | D3: Ready to build
A4: RefreshTokenTests | B4: Cookie hardening, rotation, reuse detection, logout and suspended membership | C4: 6 | D4: Ready to build
A5: PlatformAdminTests | B5: Platform admin separated from tenant data; tenant users cannot use platform endpoints | C5: 6 | D5: Ready to build
A6: HardeningTests | B6: Audit log, security headers, no-store, CORS origins and rate limiting | C6: 5 | D6: Ready to build
B7: Total expected | C7: =SUM(C2:C6) -> 28
B8: Passing and confirmed | C8: =SUMIF(D2:D6,"Done",C2:C6) -> 5
